geonames/__init__.py
geonames/geonames.csv
pygeocity-0.2.0.dist-info/LICENSE
pygeocity-0.2.0.dist-info/METADATA
pygeocity-0.2.0.dist-info/WHEEL
pygeocity-0.2.0.dist-info/top_level.txt
pygeocity-0.2.0.dist-info/RECORD
