Metadata-Version: 2.1
Name: pygeocity
Version: 0.2.0
Summary: This package will take a latitude and longitude coordinate which will return the country, city name, alternate name(s), population, timezone, and exact coordinates of the city.
Author-email: David Hintelmann <davidhin@mac.com>
Project-URL: Homepage, https://github.com/davidhintelmann/pygeocity
Project-URL: Bug Tracker, https://github.com/davidhintelmann/pygeocity/issues
Classifier: Programming Language :: Python :: 3
Classifier: License :: OSI Approved :: MIT License
Classifier: Operating System :: OS Independent
Requires-Python: >=3.11.4
License-File: LICENSE
Requires-Dist: pandas >=2.0.3
Requires-Dist: scipy >=1.11.1
Requires-Dist: numpy >=1.25.0
